lmsg/__init__.py
lmsg/_modidx.py
lmsg/base.py
lmsg/cons.py
lmsg/hush.py
lmsg/meta.py
lmsg/mixs.py
lmsg/type.py
lmsg-0.0.4.dist-info/LICENSE
lmsg-0.0.4.dist-info/METADATA
lmsg-0.0.4.dist-info/WHEEL
lmsg-0.0.4.dist-info/entry_points.txt
lmsg-0.0.4.dist-info/top_level.txt
lmsg-0.0.4.dist-info/RECORD
