Metadata-Version: 2.1
Name: lmsg
Version: 0.0.4
Summary: exceptions
Home-page: https://github.com/dsm-72/lmsg
Author: dsm-72
Author-email: sumner.magruder@yale.edu
License: Apache Software License 2.0
Keywords: exc lmsg exceptions
Classifier: Development Status :: 4 - Beta
Classifier: Intended Audience :: Developers
Classifier: Natural Language :: English
Classifier: Programming Language :: Python :: 3.11
Classifier: License :: OSI Approved :: Apache Software License
Requires-Python: >=3.11
License-File: LICENSE
Provides-Extra: dev
